mac_formatter/__init__.py
mac_formatter/cli.py
mac_formatter/mac_formatter.py
mac_formatter-0.4.0.dist-info/METADATA
mac_formatter-0.4.0.dist-info/WHEEL
mac_formatter-0.4.0.dist-info/entry_points.txt
mac_formatter-0.4.0.dist-info/top_level.txt
mac_formatter-0.4.0.dist-info/RECORD
