Metadata-Version: 2.1
Name: mac-formatter
Version: 0.4.0
Summary: A simple tool for formatting MAC addresses
Author: thamuppet
